wofrysrw/__init__.py
wofrysrw/srw_object.py
wofrysrw/beamline/__init__.py
wofrysrw/beamline/srw_beamline.py
wofrysrw/beamline/optical_elements/__init__.py
wofrysrw/beamline/optical_elements/srw_optical_element.py
wofrysrw/beamline/optical_elements/absorbers/__init__.py
wofrysrw/beamline/optical_elements/absorbers/srw_aperture.py
wofrysrw/beamline/optical_elements/absorbers/srw_filter.py
wofrysrw/beamline/optical_elements/absorbers/srw_obstacle.py
wofrysrw/beamline/optical_elements/absorbers/srw_slit.py
wofrysrw/beamline/optical_elements/absorbers/srw_transmission.py
wofrysrw/beamline/optical_elements/crystals/__init__.py
wofrysrw/beamline/optical_elements/crystals/srw_crystal.py
wofrysrw/beamline/optical_elements/gratings/srw_elliptical_grating.py
wofrysrw/beamline/optical_elements/gratings/srw_grating.py
wofrysrw/beamline/optical_elements/gratings/srw_plain_grating.py
wofrysrw/beamline/optical_elements/ideal_elements/__init__.py
wofrysrw/beamline/optical_elements/ideal_elements/srw_ideal_lens.py
wofrysrw/beamline/optical_elements/ideal_elements/srw_screen.py
wofrysrw/beamline/optical_elements/mirrors/__init__.py
wofrysrw/beamline/optical_elements/mirrors/srw_elliptical_mirror.py
wofrysrw/beamline/optical_elements/mirrors/srw_mirror.py
wofrysrw/beamline/optical_elements/mirrors/srw_plane_mirror.py
wofrysrw/beamline/optical_elements/mirrors/srw_spherical_mirror.py
wofrysrw/beamline/optical_elements/mirrors/srw_toroidal_mirror.py
wofrysrw/beamline/optical_elements/other/__init__.py
wofrysrw/beamline/optical_elements/other/srw_crl.py
wofrysrw/beamline/optical_elements/other/srw_zone_plate.py
wofrysrw/propagator/__init__.py
wofrysrw/propagator/propagators2D/__init__.py
wofrysrw/propagator/propagators2D/srw_fresnel_native.py
wofrysrw/propagator/propagators2D/srw_fresnel_wofry.py
wofrysrw/propagator/propagators2D/srw_propagation_mode.py
wofrysrw/propagator/wavefront2D/__init__.py
wofrysrw/propagator/wavefront2D/srw_wavefront.py
wofrysrw/storage_ring/__init__.py
wofrysrw-1.1.35.dist-info/licenses/LICENSE
wofrysrw-1.1.35.dist-info/METADATA
wofrysrw-1.1.35.dist-info/WHEEL
wofrysrw-1.1.35.dist-info/top_level.txt
wofrysrw-1.1.35.dist-info/RECORD
