Metadata-Version: 2.4
Name: wofrysrw
Version: 1.1.35
Summary: WOFRY for SRW library
Home-page: https://github.com/lucarebuffi/wofrysrw
Download-URL: https://github.com/lucarebuffi/wofrysrw
Author: Luca Rebuffi
Author-email: lrebuffi@anl.gov
License: GPLv3
Keywords: dictionary,glossary,synchrotronsimulation
Classifier: Development Status :: 4 - Beta
Classifier: Environment :: X11 Applications :: Qt
Classifier: Environment :: Console
Classifier: Environment :: Plugins
Classifier: Programming Language :: Python :: 3
Classifier: Intended Audience :: Science/Research
License-File: LICENSE
Requires-Dist: setuptools
Requires-Dist: wofry>=1.0.31
Dynamic: author
Dynamic: author-email
Dynamic: classifier
Dynamic: description
Dynamic: download-url
Dynamic: home-page
Dynamic: keywords
Dynamic: license
Dynamic: license-file
Dynamic: requires-dist
Dynamic: summary
